link/__init__.py
link/json/__init__.py
link/json/collection.py
link/json/exceptions.py
link/json/generator.py
link/json/resolver.py
link/json/schema.py
link/json/transform.py
link.json-0.11.dist-info/DESCRIPTION.rst
link.json-0.11.dist-info/METADATA
link.json-0.11.dist-info/RECORD
link.json-0.11.dist-info/WHEEL
link.json-0.11.dist-info/metadata.json
link.json-0.11.dist-info/top_level.txt
