Metadata-Version: 2.0
Name: link.json
Version: 0.11
Summary: Provides utilities for JSON Schema, JSON Patch, Collection+JSON, ...
Home-page: https://github.com/linkdd/link.json
Author: David Delassus
Author-email: david.jose.delassus@gmail.com
License: MIT
Keywords: link json
Platform: UNKNOWN
Classifier: Development Status :: 4 - Beta
Classifier: License :: OSI Approved :: MIT License
Classifier: Operating System :: OS Independent
Classifier: Topic :: Utilities
Classifier: Topic :: Software Development :: Libraries :: Python Modules
Classifier: Intended Audience :: Developers
Classifier: Programming Language :: Python
Classifier: Programming Language :: Python :: 2.7
Classifier: Programming Language :: Python :: 3
Classifier: Programming Language :: Python :: 3.4
Classifier: Programming Language :: Python :: 3.5
Classifier: Programming Language :: Python :: Implementation :: CPython
Requires-Dist: b3j0f.conf (>=0.3.19)
Requires-Dist: jsonpatch (>=1.13)
Requires-Dist: jsonschema (>=2.5.1)
Requires-Dist: link.middleware (>=1.5)
